gmail_python_client/__init__.py
gmail_python_client/email_client.py
gmail_python_client/gmail_client.py
gmail_python_client-0.0.4.dist-info/LICENSE
gmail_python_client-0.0.4.dist-info/METADATA
gmail_python_client-0.0.4.dist-info/WHEEL
gmail_python_client-0.0.4.dist-info/top_level.txt
gmail_python_client-0.0.4.dist-info/RECORD
