Metadata-Version: 2.1
Name: gmail-python-client
Version: 0.0.4
Summary: Client for Sending Emails via GMail using OAuth2.0
Home-page: https://github.com/Topazoo/Gmail-Python-Client
Author: Peter Swanson
Author-email: pswanson@ucdavis.edu
License: LICENSE
Platform: UNKNOWN
Requires-Python: >=3.9
License-File: LICENSE
Requires-Dist: google-api-python-client ==2.36.0
Requires-Dist: google-auth-oauthlib ==0.4.6
